easyasr/__init__.py
easytransfer/__init__.py
easyvision/__init__.py
easyasr-0.0.1.dist-info/LICENSE
easyasr-0.0.1.dist-info/METADATA
easyasr-0.0.1.dist-info/WHEEL
easyasr-0.0.1.dist-info/top_level.txt
easyasr-0.0.1.dist-info/RECORD
