Metadata-Version: 2.1
Name: easyasr
Version: 0.0.1
Summary: PAI EasyASR Toolkit
Home-page: https://github.com/pypa/sampleproject
Author: PAI NLP
Author-email: minghui.qmh@alibaba-inc.com
License: Apache-2.0
Platform: UNKNOWN
Requires-Python: >=2.7
Requires-Dist: numpy
Requires-Dist: sklearn
Requires-Dist: sentencepiece
Provides-Extra: tf
Requires-Dist: tensorflow (==1.12) ; extra == 'tf'
Provides-Extra: tf_gpu
Requires-Dist: tensorflow-gpu (==1.12) ; extra == 'tf_gpu'
